my_own_package/__init__.py
Melinte_Tiberiu_own_first_package-0.1.0.dist-info/METADATA
Melinte_Tiberiu_own_first_package-0.1.0.dist-info/WHEEL
Melinte_Tiberiu_own_first_package-0.1.0.dist-info/top_level.txt
Melinte_Tiberiu_own_first_package-0.1.0.dist-info/RECORD
