Metadata-Version: 2.1
Name: Melinte-Tiberiu-own-first-package
Version: 0.1.0
Summary: This my first package
Author: Melinte Tiberiu
Author-email: melintetiberiu@yahoo.com
